cardcanvas/__init__.py
cardcanvas/card_manager.py
cardcanvas/helpers.py
cardcanvas/main.py
cardcanvas/settings.py
cardcanvas/ui.py
cardcanvas/assets/main.css
cardcanvas-0.8.0.dist-info/METADATA
cardcanvas-0.8.0.dist-info/WHEEL
cardcanvas-0.8.0.dist-info/licenses/LICENSE
cardcanvas-0.8.0.dist-info/RECORD
