Metadata-Version: 2.4
Name: cardcanvas
Version: 0.8.0
Summary: Configurable dashboard with dash
Author-email: Najeem Muhammed <najeem@gmail.com>
License-File: LICENSE
Requires-Python: >=3.10
Requires-Dist: dash-iconify>=0.1.2
Requires-Dist: dash-mantine-components>=2.3.0
Requires-Dist: dash-snap-grid>=0.4.2
Requires-Dist: dash>=3.2.0
